full_adder.v
module full_adder(
    input A,
    input B,
    input Cin,
    output Sum,
    output Cout
);

assign Cout=A&B|A&Cin|B&Cin;
assign Sum=A^B^Cin;

endmodule

full_adder_tb.v
module full_adder_tb;

reg A, B, Cin;
wire Sum,Cout;


full_adder uut(
    .A(A),
    .B(B),
    .Cin(Cin),
    .Sum(Sum),
    .Cout(Cout)
);

initial begin
$dumpfile("full_adder.vcd");
$dumpvars(0, full_adder_tb);
A=0; B=0; Cin=0; #10;
A=0; B=0; Cin=1; #10;  
A=0; B=1; Cin=0; #10;
A=0; B=1; Cin=1; #10;
A=1; B=0; Cin=0; #10;
A=1; B=0; Cin=1; #10;
A=1; B=1; Cin=0; #10;
A=1; B=1; Cin=1; #10;
$finish;
end

endmodule

full_adder.vcd
$date
	Tue Feb 24 19:53:24 2026
$end
$version
	Icarus Verilog
$end
$timescale
	1s
$end
$scope module full_adder_tb $end
$var wire 1 ! Sum $end
$var wire 1 " Cout $end
$var reg 1 # A $end
$var reg 1 $ B $end
$var reg 1 % Cin $end
$scope module uut $end
$var wire 1 # A $end
$var wire 1 $ B $end
$var wire 1 % Cin $end
$var wire 1 " Cout $end
$var wire 1 ! Sum $end
$upscope $end
$upscope $end
$enddefinitions $end
$comment Show the parameter values. $end
$dumpall
$end
#0
$dumpvars
0%
0$
0#
0"
0!
$end
#10
1!
1%
#20
0%
1$
#30
1"
0!
1%
#40
0"
1!
0%
0$
1#
#50
1"
0!
1%
#60
0%
1$
#70
1!
1%
