majority.v
module majority (
    input A,
    input B,
    input C,
    output F
);

assign F = (A & B) | (A & C) | (B & C);

endmodule

majority_tb.v
module majority_tb;

reg A;
reg B;
reg C;
wire F;

// Instantiate the module
majority uut (
    .A(A),
    .B(B),
    .C(C),
    .F(F)
);

initial begin
    $dumpfile("majority.vcd");
    $dumpvars(0, majority_tb);

    // Test all combinations
    A=0; B=0; C=0; #10;
    A=0; B=0; C=1; #10;
    A=0; B=1; C=0; #10;
    A=0; B=1; C=1; #10;
    A=1; B=0; C=0; #10;
    A=1; B=0; C=1; #10;
    A=1; B=1; C=0; #10;
    A=1; B=1; C=1; #10;

    $finish;
end

endmodule

majority.vcd
$date
	Wed Feb 18 21:32:34 2026
$end
$version
	Icarus Verilog
$end
$timescale
	1s
$end
$scope module majority_tb $end
$var wire 1 ! F $end
$var reg 1 " A $end
$var reg 1 # B $end
$var reg 1 $ C $end
$scope module uut $end
$var wire 1 " A $end
$var wire 1 # B $end
$var wire 1 $ C $end
$var wire 1 ! F $end
$upscope $end
$upscope $end
$enddefinitions $end
$comment Show the parameter values. $end
$dumpall
$end
#0
$dumpvars
0$
0#
0"
0!
$end
#10
1$
#20
0$
1#
#30
1!
1$
#40
0!
0$
0#
1"
#50
1!
1$
#60
0$
1#
#70
1$
